<root>
    <file perm="0644" size="57427618" path="/rpm" name="intel-advisor-2017-cli-17.1-510716.i486.rpm" cksum="624938514"/>
    <file perm="0644" size="65790599" path="/rpm" name="intel-advisor-2017-cli-17.1-510716.x86_64.rpm" cksum="322207965"/>
    <file perm="0644" size="233431" path="/rpm" name="intel-advisor-2017-cli-common-17.1-510716.noarch.rpm" cksum="3087638485"/>
    <file perm="0644" size="37443955" path="/rpm" name="intel-advisor-2017-cli-pset-17.1-510716.noarch.rpm" cksum="750895443"/>
    <file perm="0644" size="12594391" path="/rpm" name="intel-advisor-2017-doc-17.1-510716.noarch.rpm" cksum="183733938"/>
    <file perm="0644" size="28849803" path="/rpm" name="intel-advisor-2017-gui-17.1-510716.i486.rpm" cksum="2611707166"/>
    <file perm="0644" size="30717757" path="/rpm" name="intel-advisor-2017-gui-17.1-510716.x86_64.rpm" cksum="4109188555"/>
    <file perm="0644" size="1276964" path="/rpm" name="intel-advisor-2017-gui-common-17.1-510716.noarch.rpm" cksum="4175929160"/>
    <file perm="0644" size="8170" path="/rpm" name="intel-comp-all-doc-17.0.4-196.noarch.rpm" cksum="2919908221"/>
    <file perm="0644" size="4809349" path="/rpm" name="intel-comp-l-all-196-17.0.4-196.x86_64.rpm" cksum="1641584319"/>
    <file perm="0644" size="74072" path="/rpm" name="intel-comp-l-all-common-196-17.0.4-196.noarch.rpm" cksum="1907487750"/>
    <file perm="0644" size="17504" path="/rpm" name="intel-comp-l-all-vars-196-17.0.4-196.noarch.rpm" cksum="4029360976"/>
    <file perm="0644" size="3185887" path="/rpm" name="intel-comp-l-all-wrapper-196-17.0.4-196.x86_64.rpm" cksum="1563173424"/>
    <file perm="0644" size="5092209" path="/rpm" name="intel-comp-l-ps-196-17.0.4-196.x86_64.rpm" cksum="1162113509"/>
    <file perm="0644" size="342329" path="/rpm" name="intel-comp-l-ps-ss-196-17.0.4-196.x86_64.rpm" cksum="1712875307"/>
    <file perm="0644" size="111108" path="/rpm" name="intel-comp-l-ps-ss-bec-196-17.0.4-196.x86_64.rpm" cksum="377688265"/>
    <file perm="0644" size="89303" path="/rpm" name="intel-comp-l-ps-ss-bec-wrapper-196-17.0.4-196.x86_64.rpm" cksum="2343241700"/>
    <file perm="0644" size="6721" path="/rpm" name="intel-comp-l-ss-doc-17.0.4-196.x86_64.rpm" cksum="1947064052"/>
    <file perm="0644" size="8489" path="/rpm" name="intel-comp-ps-doc-jp-17.0.4-196.noarch.rpm" cksum="586386835"/>
    <file perm="0644" size="219268133" path="/rpm" name="intel-daal-196-2017.3-196.i486.rpm" cksum="1054400585"/>
    <file perm="0644" size="281203393" path="/rpm" name="intel-daal-196-2017.3-196.x86_64.rpm" cksum="126527959"/>
    <file perm="0644" size="31670863" path="/rpm" name="intel-daal-common-196-2017.3-196.noarch.rpm" cksum="2331794471"/>
    <file perm="0644" size="212616" path="/rpm" name="intel-daal-doc-2017.3-196.noarch.rpm" cksum="2266486007"/>
    <file perm="0644" size="8117" path="/rpm" name="intel-daal-ps-common-jp-196-2017.3-196.noarch.rpm" cksum="3722342912"/>
    <file perm="0644" size="4661844" path="/rpm" name="intel-daal-ps-doc-jp-2017.3-196.noarch.rpm" cksum="1118463889"/>
    <file perm="0644" size="22128656" path="/rpm" name="intel-gdb-2017.3-196.x86_64.rpm" cksum="725696698"/>
    <file perm="0644" size="45588" path="/rpm" name="intel-gdb-common-2017.3-196.noarch.rpm" cksum="3981267049"/>
    <file perm="0644" size="3279373" path="/rpm" name="intel-gdb-doc-2017.3-196.noarch.rpm" cksum="1813818551"/>
    <file perm="0644" size="4480850" path="/rpm" name="intel-gdb-gt-2017.3-196.x86_64.rpm" cksum="4067913186"/>
    <file perm="0644" size="3034341" path="/rpm" name="intel-gdb-gt-doc-2017.3-196.noarch.rpm" cksum="329080049"/>
    <file perm="0644" size="2998015" path="/rpm" name="intel-gdb-gt-doc-jp-2017.3-196.noarch.rpm" cksum="986505216"/>
    <file perm="0644" size="35460667" path="/rpm" name="intel-gdb-gt-src-2017.3-196.noarch.rpm" cksum="4067886050"/>
    <file perm="0644" size="593216" path="/rpm" name="intel-gdb-ps-doc-2017.3-056.noarch.rpm" cksum="3157548995"/>
    <file perm="0644" size="3869406" path="/rpm" name="intel-gdb-ps-doc-jp-2017.3-056.noarch.rpm" cksum="3173630394"/>
    <file perm="0644" size="6554420" path="/rpm" name="intel-gdb-ps-mic-2017.3-056.x86_64.rpm" cksum="1222655960"/>
    <file perm="0644" size="124534" path="/rpm" name="intel-gdb-ps-mic-cdt-2017.3-056.x86_64.rpm" cksum="1000750839"/>
    <file perm="0644" size="47897928" path="/rpm" name="intel-gdb-ps-mic-cdt-source-2017.3-056.noarch.rpm" cksum="183435662"/>
    <file perm="0644" size="3291545" path="/rpm" name="intel-gdb-ps-mic-doc-2017.3-056.noarch.rpm" cksum="1754939789"/>
    <file perm="0644" size="3291578" path="/rpm" name="intel-gdb-ps-mic-doc-jp-2017.3-056.noarch.rpm" cksum="3781659428"/>
    <file perm="0644" size="481184" path="/rpm" name="intel-gdb-ps-mic-mpm-2017.3-056.x86_64.rpm" cksum="4264094395"/>
    <file perm="0644" size="45013057" path="/rpm" name="intel-gdb-ps-mic-source-2017.3-056.noarch.rpm" cksum="1221925769"/>
    <file perm="0644" size="16892865" path="/rpm" name="intel-gdb-python-source-2017.3-196.noarch.rpm" cksum="2564685997"/>
    <file perm="0644" size="32679694" path="/rpm" name="intel-gdb-source-2017.3-196.noarch.rpm" cksum="1009032352"/>
    <file perm="0644" size="129796" path="/rpm" name="intel-icc-doc-17.0.4-196.noarch.rpm" cksum="2517559094"/>
    <file perm="0644" size="26806998" path="/rpm" name="intel-icc-l-all-196-17.0.4-196.x86_64.rpm" cksum="3775300556"/>
    <file perm="0644" size="366229" path="/rpm" name="intel-icc-l-all-common-196-17.0.4-196.noarch.rpm" cksum="3344971409"/>
    <file perm="0644" size="6306" path="/rpm" name="intel-icc-l-all-common-jp-196-17.0.4-196.noarch.rpm" cksum="2600643520"/>
    <file perm="0644" size="709564" path="/rpm" name="intel-icc-l-all-wrapper-196-17.0.4-196.x86_64.rpm" cksum="3985015838"/>
    <file perm="0644" size="21177222" path="/rpm" name="intel-icc-l-ps-196-17.0.4-196.x86_64.rpm" cksum="3037471649"/>
    <file perm="0644" size="5922" path="/rpm" name="intel-icc-l-ps-common-196-17.0.4-196.noarch.rpm" cksum="1002285732"/>
    <file perm="0644" size="32034166" path="/rpm" name="intel-icc-l-ps-ss-196-17.0.4-196.x86_64.rpm" cksum="734283308"/>
    <file perm="0644" size="21592" path="/rpm" name="intel-icc-l-ps-ss-bec-196-17.0.4-196.x86_64.rpm" cksum="4293673029"/>
    <file perm="0644" size="142386" path="/rpm" name="intel-icc-l-ps-ss-bec-common-196-17.0.4-196.noarch.rpm" cksum="3470656913"/>
    <file perm="0644" size="21441" path="/rpm" name="intel-icc-l-ps-ss-bec-wrapper-196-17.0.4-196.x86_64.rpm" cksum="1789058143"/>
    <file perm="0644" size="1017852" path="/rpm" name="intel-icc-ps-doc-17.0.4-196.noarch.rpm" cksum="1213737138"/>
    <file perm="0644" size="7050050" path="/rpm" name="intel-icc-ps-doc-jp-17.0.4-196.noarch.rpm" cksum="3877085210"/>
    <file perm="0644" size="7173527" path="/rpm" name="intel-icc-ps-ss-doc-17.0.4-196.noarch.rpm" cksum="3005052318"/>
    <file perm="0644" size="9310" path="/rpm" name="intel-icsxe-056-2017.4-056.noarch.rpm" cksum="2758429763"/>
    <file perm="0644" size="14223" path="/rpm" name="intel-icsxe-doc-2017.4-056.noarch.rpm" cksum="2453095600"/>
    <file perm="0644" size="20029168" path="/rpm" name="intel-icsxe-pset-056-2017.4-056.noarch.rpm" cksum="331541425"/>
    <file perm="0644" size="51008588" path="/rpm" name="intel-ifort-l-ps-196-17.0.4-196.x86_64.rpm" cksum="2665177766"/>
    <file perm="0644" size="77940" path="/rpm" name="intel-ifort-l-ps-common-196-17.0.4-196.noarch.rpm" cksum="667558108"/>
    <file perm="0644" size="5049" path="/rpm" name="intel-ifort-l-ps-common-jp-196-17.0.4-196.noarch.rpm" cksum="2311625610"/>
    <file perm="0644" size="204935" path="/rpm" name="intel-ifort-l-ps-jp-196-17.0.4-196.x86_64.rpm" cksum="3720480081"/>
    <file perm="0644" size="3871392" path="/rpm" name="intel-ifort-l-ps-wrapper-196-17.0.4-196.x86_64.rpm" cksum="312931083"/>
    <file perm="0644" size="16594" path="/rpm" name="intel-ifort-l-ps-wrapper-jp-196-17.0.4-196.x86_64.rpm" cksum="65905246"/>
    <file perm="0644" size="9312851" path="/rpm" name="intel-ifort-ps-doc-17.0.4-196.noarch.rpm" cksum="3916050101"/>
    <file perm="0644" size="8701582" path="/rpm" name="intel-ifort-ps-doc-jp-17.0.4-196.noarch.rpm" cksum="2195183175"/>
    <file perm="0644" size="1701409" path="/rpm" name="intel-imb-196-2017.3-196.x86_64.rpm" cksum="1433893243"/>
    <file perm="0644" size="22761359" path="/rpm" name="intel-inspector-2017-cli-17.1-510645.i486.rpm" cksum="1789075544"/>
    <file perm="0644" size="24700677" path="/rpm" name="intel-inspector-2017-cli-17.1-510645.x86_64.rpm" cksum="3978701640"/>
    <file perm="0644" size="7307343" path="/rpm" name="intel-inspector-2017-cli-common-17.1-510645.noarch.rpm" cksum="2189858714"/>
    <file perm="0644" size="37439887" path="/rpm" name="intel-inspector-2017-cli-pset-17.1-510645.noarch.rpm" cksum="3136250410"/>
    <file perm="0644" size="17768577" path="/rpm" name="intel-inspector-2017-doc-17.1-510645.noarch.rpm" cksum="3458858697"/>
    <file perm="0644" size="10929750" path="/rpm" name="intel-inspector-2017-gui-17.1-510645.i486.rpm" cksum="2053045356"/>
    <file perm="0644" size="11731889" path="/rpm" name="intel-inspector-2017-gui-17.1-510645.x86_64.rpm" cksum="1647335184"/>
    <file perm="0644" size="1872164" path="/rpm" name="intel-inspector-2017-gui-common-17.1-510645.noarch.rpm" cksum="2367440992"/>
    <file perm="0644" size="7673128" path="/rpm" name="intel-ipp-l-common-196-2017.3-196.noarch.rpm" cksum="884512894"/>
    <file perm="0644" size="8962037" path="/rpm" name="intel-ipp-l-doc-2017.3-196.noarch.rpm" cksum="3639458454"/>
    <file perm="0644" size="82160818" path="/rpm" name="intel-ipp-l-mt-196-2017.3-196.i486.rpm" cksum="1890998351"/>
    <file perm="0644" size="136887426" path="/rpm" name="intel-ipp-l-mt-196-2017.3-196.x86_64.rpm" cksum="1562035856"/>
    <file perm="0644" size="83510508" path="/rpm" name="intel-ipp-l-mt-devel-196-2017.3-196.i486.rpm" cksum="2854782505"/>
    <file perm="0644" size="144178570" path="/rpm" name="intel-ipp-l-mt-devel-196-2017.3-196.x86_64.rpm" cksum="3394630539"/>
    <file perm="0644" size="1528557" path="/rpm" name="intel-ipp-l-ps-common-196-2017.3-196.noarch.rpm" cksum="3147645855"/>
    <file perm="0644" size="8850190" path="/rpm" name="intel-ipp-l-ps-doc-jp-2017.3-196.noarch.rpm" cksum="1898822379"/>
    <file perm="0644" size="47201" path="/rpm" name="intel-ipp-l-ps-st-devel-196-2017.3-196.i486.rpm" cksum="1084035634"/>
    <file perm="0644" size="15606921" path="/rpm" name="intel-ipp-l-ps-st-devel-196-2017.3-196.x86_64.rpm" cksum="588073919"/>
    <file perm="0644" size="80068988" path="/rpm" name="intel-ipp-l-st-196-2017.3-196.i486.rpm" cksum="4202240177"/>
    <file perm="0644" size="133720732" path="/rpm" name="intel-ipp-l-st-196-2017.3-196.x86_64.rpm" cksum="1090044261"/>
    <file perm="0644" size="168064908" path="/rpm" name="intel-ipp-l-st-devel-196-2017.3-196.i486.rpm" cksum="3054305517"/>
    <file perm="0644" size="288740620" path="/rpm" name="intel-ipp-l-st-devel-196-2017.3-196.x86_64.rpm" cksum="51384042"/>
    <file perm="0644" size="40712679" path="/rpm" name="intel-ism-2.1.0.345.tgz" cksum="3447806002"/>
    <file perm="0644" size="3365706" path="/rpm" name="intel-itac-common-2017.3p-030.noarch.rpm" cksum="3267072763"/>
    <file perm="0644" size="19381442" path="/rpm" name="intel-itac-common-pset-2017.3p-030.noarch.rpm" cksum="1604646163"/>
    <file perm="0644" size="99976161" path="/rpm" name="intel-mkl-196-2017.3-196.i486.rpm" cksum="1246704501"/>
    <file perm="0644" size="167414962" path="/rpm" name="intel-mkl-196-2017.3-196.x86_64.rpm" cksum="3387822492"/>
    <file perm="0644" size="104567" path="/rpm" name="intel-mkl-common-196-2017.3-196.noarch.rpm" cksum="3073361348"/>
    <file perm="0644" size="3542" path="/rpm" name="intel-mkl-common-c-196-2017.3-196.i486.rpm" cksum="32789867"/>
    <file perm="0644" size="1826493" path="/rpm" name="intel-mkl-common-c-196-2017.3-196.noarch.rpm" cksum="555062070"/>
    <file perm="0644" size="3556" path="/rpm" name="intel-mkl-common-c-64bit-196-2017.3-196.x86_64.rpm" cksum="1789793792"/>
    <file perm="0644" size="725452" path="/rpm" name="intel-mkl-doc-2017.3-196.noarch.rpm" cksum="3241088915"/>
    <file perm="0644" size="7330277" path="/rpm" name="intel-mkl-doc-c-2017.3-196.noarch.rpm" cksum="3093001699"/>
    <file perm="0644" size="2813064" path="/rpm" name="intel-mkl-gnu-196-2017.3-196.i486.rpm" cksum="2715979754"/>
    <file perm="0644" size="6329476" path="/rpm" name="intel-mkl-gnu-196-2017.3-196.x86_64.rpm" cksum="3284131561"/>
    <file perm="0644" size="3520" path="/rpm" name="intel-mkl-gnu-c-196-2017.3-196.i486.rpm" cksum="3624248410"/>
    <file perm="0644" size="3522" path="/rpm" name="intel-mkl-gnu-c-196-2017.3-196.x86_64.rpm" cksum="1843715793"/>
    <file perm="0644" size="2578227" path="/rpm" name="intel-mkl-gnu-rt-196-2017.3-196.i486.rpm" cksum="73270170"/>
    <file perm="0644" size="5671564" path="/rpm" name="intel-mkl-gnu-rt-196-2017.3-196.x86_64.rpm" cksum="1422711470"/>
    <file perm="0644" size="111964" path="/rpm" name="intel-mkl-ps-cluster-196-2017.3-196.noarch.rpm" cksum="2446739958"/>
    <file perm="0644" size="7597320" path="/rpm" name="intel-mkl-ps-cluster-64bit-196-2017.3-196.x86_64.rpm" cksum="1594497516"/>
    <file perm="0644" size="3454" path="/rpm" name="intel-mkl-ps-cluster-c-196-2017.3-196.noarch.rpm" cksum="3284853422"/>
    <file perm="0644" size="3452" path="/rpm" name="intel-mkl-ps-cluster-f-196-2017.3-196.noarch.rpm" cksum="1943980330"/>
    <file perm="0644" size="6463557" path="/rpm" name="intel-mkl-ps-cluster-rt-196-2017.3-196.x86_64.rpm" cksum="2473627350"/>
    <file perm="0644" size="1533540" path="/rpm" name="intel-mkl-ps-common-196-2017.3-196.i486.rpm" cksum="2833411523"/>
    <file perm="0644" size="123256" path="/rpm" name="intel-mkl-ps-common-196-2017.3-196.noarch.rpm" cksum="3046629189"/>
    <file perm="0644" size="13071165" path="/rpm" name="intel-mkl-ps-common-64bit-196-2017.3-196.x86_64.rpm" cksum="4116134156"/>
    <file perm="0644" size="76977" path="/rpm" name="intel-mkl-ps-common-c-196-2017.3-196.noarch.rpm" cksum="896733366"/>
    <file perm="0644" size="3555" path="/rpm" name="intel-mkl-ps-common-f-196-2017.3-196.i486.rpm" cksum="433668841"/>
    <file perm="0644" size="2142754" path="/rpm" name="intel-mkl-ps-common-f-196-2017.3-196.noarch.rpm" cksum="3477982767"/>
    <file perm="0644" size="3570" path="/rpm" name="intel-mkl-ps-common-f-64bit-196-2017.3-196.x86_64.rpm" cksum="624715634"/>
    <file perm="0644" size="6292" path="/rpm" name="intel-mkl-ps-common-jp-196-2017.3-196.noarch.rpm" cksum="1951392035"/>
    <file perm="0644" size="58164" path="/rpm" name="intel-mkl-ps-doc-2017.3-196.noarch.rpm" cksum="3021188162"/>
    <file perm="0644" size="7330205" path="/rpm" name="intel-mkl-ps-doc-c-jp-2017.3-196.noarch.rpm" cksum="4093446243"/>
    <file perm="0644" size="8054318" path="/rpm" name="intel-mkl-ps-doc-f-2017.3-196.noarch.rpm" cksum="3178995806"/>
    <file perm="0644" size="8054180" path="/rpm" name="intel-mkl-ps-doc-f-jp-2017.3-196.noarch.rpm" cksum="972472698"/>
    <file perm="0644" size="596142" path="/rpm" name="intel-mkl-ps-doc-jp-2017.3-196.noarch.rpm" cksum="3631355496"/>
    <file perm="0644" size="2372230" path="/rpm" name="intel-mkl-ps-f95-196-2017.3-196.i486.rpm" cksum="1418076624"/>
    <file perm="0644" size="5089398" path="/rpm" name="intel-mkl-ps-f95-196-2017.3-196.x86_64.rpm" cksum="217794677"/>
    <file perm="0644" size="430971" path="/rpm" name="intel-mkl-ps-f95-common-196-2017.3-196.noarch.rpm" cksum="3393374492"/>
    <file perm="0644" size="16464266" path="/rpm" name="intel-mkl-ps-f95-mic-196-2017.3-196.x86_64.rpm" cksum="2263508086"/>
    <file perm="0644" size="1802557" path="/rpm" name="intel-mkl-ps-gnu-f-196-2017.3-196.i486.rpm" cksum="2353818970"/>
    <file perm="0644" size="5011177" path="/rpm" name="intel-mkl-ps-gnu-f-196-2017.3-196.x86_64.rpm" cksum="3530522035"/>
    <file perm="0644" size="1760650" path="/rpm" name="intel-mkl-ps-gnu-f-rt-196-2017.3-196.i486.rpm" cksum="1898878465"/>
    <file perm="0644" size="4529846" path="/rpm" name="intel-mkl-ps-gnu-f-rt-196-2017.3-196.x86_64.rpm" cksum="660097294"/>
    <file perm="0644" size="81096933" path="/rpm" name="intel-mkl-ps-mic-196-2017.3-196.x86_64.rpm" cksum="3075409552"/>
    <file perm="0644" size="31201" path="/rpm" name="intel-mkl-ps-mic-c-196-2017.3-196.x86_64.rpm" cksum="3332575059"/>
    <file perm="0644" size="9881999" path="/rpm" name="intel-mkl-ps-mic-cluster-196-2017.3-196.x86_64.rpm" cksum="359669506"/>
    <file perm="0644" size="8501082" path="/rpm" name="intel-mkl-ps-mic-cluster-rt-196-2017.3-196.x86_64.rpm" cksum="1330729503"/>
    <file perm="0644" size="10929" path="/rpm" name="intel-mkl-ps-mic-f-196-2017.3-196.x86_64.rpm" cksum="35000588"/>
    <file perm="0644" size="95025200" path="/rpm" name="intel-mkl-ps-mic-rt-196-2017.3-196.x86_64.rpm" cksum="1636351179"/>
    <file perm="0644" size="30992" path="/rpm" name="intel-mkl-ps-mic-rt-jp-196-2017.3-196.x86_64.rpm" cksum="1362220761"/>
    <file perm="0644" size="9054702" path="/rpm" name="intel-mkl-ps-pgi-196-2017.3-196.x86_64.rpm" cksum="1684176311"/>
    <file perm="0644" size="3535" path="/rpm" name="intel-mkl-ps-pgi-c-196-2017.3-196.x86_64.rpm" cksum="2731058361"/>
    <file perm="0644" size="3532" path="/rpm" name="intel-mkl-ps-pgi-f-196-2017.3-196.x86_64.rpm" cksum="356274327"/>
    <file perm="0644" size="7300649" path="/rpm" name="intel-mkl-ps-pgi-rt-196-2017.3-196.x86_64.rpm" cksum="1361652460"/>
    <file perm="0644" size="30950" path="/rpm" name="intel-mkl-ps-rt-jp-196-2017.3-196.i486.rpm" cksum="81389703"/>
    <file perm="0644" size="30957" path="/rpm" name="intel-mkl-ps-rt-jp-196-2017.3-196.x86_64.rpm" cksum="2096380969"/>
    <file perm="0644" size="1840775" path="/rpm" name="intel-mkl-ps-ss-tbb-196-2017.3-196.i486.rpm" cksum="2744605179"/>
    <file perm="0644" size="5345802" path="/rpm" name="intel-mkl-ps-ss-tbb-196-2017.3-196.x86_64.rpm" cksum="2239211317"/>
    <file perm="0644" size="1732120" path="/rpm" name="intel-mkl-ps-ss-tbb-rt-196-2017.3-196.i486.rpm" cksum="634652934"/>
    <file perm="0644" size="4902108" path="/rpm" name="intel-mkl-ps-ss-tbb-rt-196-2017.3-196.x86_64.rpm" cksum="3525690422"/>
    <file perm="0644" size="9080739" path="/rpm" name="intel-mkl-ps-tbb-mic-196-2017.3-196.x86_64.rpm" cksum="1665116229"/>
    <file perm="0644" size="8430790" path="/rpm" name="intel-mkl-ps-tbb-mic-rt-196-2017.3-196.x86_64.rpm" cksum="454752680"/>
    <file perm="0644" size="100114883" path="/rpm" name="intel-mkl-rt-196-2017.3-196.i486.rpm" cksum="3953636102"/>
    <file perm="0644" size="161208021" path="/rpm" name="intel-mkl-rt-196-2017.3-196.x86_64.rpm" cksum="1592768546"/>
    <file perm="0644" size="2961067" path="/rpm" name="intel-mpi-doc-2017.3-196.x86_64.rpm" cksum="1938716237"/>
    <file perm="0644" size="13916211" path="/rpm" name="intel-mpi-rt-core-196-2017.3-196.x86_64.rpm" cksum="3944387747"/>
    <file perm="0644" size="9901923" path="/rpm" name="intel-mpi-rt-mic-196-2017.3-196.x86_64.rpm" cksum="1732195763"/>
    <file perm="0644" size="5786" path="/rpm" name="intel-mpi-samples-196-2017.3-196.x86_64.rpm" cksum="1868510080"/>
    <file perm="0644" size="126663297" path="/rpm" name="intel-mpi-sdk-core-196-2017.3-196.x86_64.rpm" cksum="871517694"/>
    <file perm="0644" size="119823846" path="/rpm" name="intel-mpi-sdk-mic-196-2017.3-196.x86_64.rpm" cksum="3372734153"/>
    <file perm="0644" size="2484903" path="/rpm" name="intel-mpirt-l-ps-wrapper-196-17.0.4-196.x86_64.rpm" cksum="2636837914"/>
    <file perm="0644" size="1954551" path="/rpm" name="intel-openmp-l-all-196-17.0.4-196.i486.rpm" cksum="858482879"/>
    <file perm="0644" size="2011618" path="/rpm" name="intel-openmp-l-all-196-17.0.4-196.x86_64.rpm" cksum="2814828064"/>
    <file perm="0644" size="411436" path="/rpm" name="intel-openmp-l-ps-196-17.0.4-196.i486.rpm" cksum="2520001559"/>
    <file perm="0644" size="12468192" path="/rpm" name="intel-openmp-l-ps-196-17.0.4-196.x86_64.rpm" cksum="2880234169"/>
    <file perm="0644" size="11717" path="/rpm" name="intel-openmp-l-ps-bec-196-17.0.4-196.x86_64.rpm" cksum="3562638842"/>
    <file perm="0644" size="7873" path="/rpm" name="intel-openmp-l-ps-jp-196-17.0.4-196.i486.rpm" cksum="2244988308"/>
    <file perm="0644" size="217270" path="/rpm" name="intel-openmp-l-ps-jp-196-17.0.4-196.x86_64.rpm" cksum="559695618"/>
    <file perm="0644" size="1965026" path="/rpm" name="intel-openmp-l-ps-libs-196-17.0.4-196.x86_64.rpm" cksum="2203514547"/>
    <file perm="0644" size="14988" path="/rpm" name="intel-openmp-l-ps-libs-jp-196-17.0.4-196.i486.rpm" cksum="3018165218"/>
    <file perm="0644" size="15001" path="/rpm" name="intel-openmp-l-ps-libs-jp-196-17.0.4-196.x86_64.rpm" cksum="1459568981"/>
    <file perm="0644" size="412199" path="/rpm" name="intel-openmp-l-ps-ss-196-17.0.4-196.x86_64.rpm" cksum="3167383802"/>
    <file perm="0644" size="21589594" path="/rpm" name="intel-openmp-l-ps-ss-bec-196-17.0.4-196.i486.rpm" cksum="2730268432"/>
    <file perm="0644" size="20926539" path="/rpm" name="intel-openmp-l-ps-ss-bec-196-17.0.4-196.x86_64.rpm" cksum="2840990756"/>
    <file perm="0644" size="5736" path="/rpm" name="intel-psxe-common-056-2017.4-056.noarch.rpm" cksum="1165768655"/>
    <file perm="0644" size="883973" path="/rpm" name="intel-psxe-common-doc-2017.4-056.noarch.rpm" cksum="387110269"/>
    <file perm="0644" size="1126368" path="/rpm" name="intel-psxe-doc-2017.4-056.noarch.rpm" cksum="2406718924"/>
    <file perm="0644" size="31212" path="/rpm" name="intel-psxe-licensing-056-2017.4-056.noarch.rpm" cksum="1418558258"/>
    <file perm="0644" size="31097" path="/rpm" name="intel-psxe-licensing-doc-2017.4-056.noarch.rpm" cksum="1148932339"/>
    <file perm="0644" size="43144322" path="/rpm" name="intel-ta-2017.3p-030.x86_64.rpm" cksum="3860973094"/>
    <file perm="0644" size="13049842" path="/rpm" name="intel-tbb-common-196-2017.6-196.noarch.rpm" cksum="1780686493"/>
    <file perm="0644" size="8828" path="/rpm" name="intel-tbb-common-jp-196-2017.6-196.noarch.rpm" cksum="2037634278"/>
    <file perm="0644" size="328963" path="/rpm" name="intel-tbb-devel-196-2017.6-196.noarch.rpm" cksum="596935328"/>
    <file perm="0644" size="1963912" path="/rpm" name="intel-tbb-doc-2017.6-196.noarch.rpm" cksum="2295372155"/>
    <file perm="0644" size="2092496" path="/rpm" name="intel-tbb-doc-jp-2017.6-196.noarch.rpm" cksum="3303594836"/>
    <file perm="0644" size="5115005" path="/rpm" name="intel-tbb-libs-196-2017.6-196.noarch.rpm" cksum="2003109971"/>
    <file perm="0644" size="2601551" path="/rpm" name="intel-tbb-ps-common-196-2017.6-196.noarch.rpm" cksum="1346386207"/>
    <file perm="0644" size="56596898" path="/rpm" name="intel-tc-2017.3p-030.x86_64.rpm" cksum="2356538480"/>
    <file perm="0644" size="41189070" path="/rpm" name="intel-tc-mic-2017.3p-030.x86_64.rpm" cksum="2985474720"/>
    <file perm="0644" size="54567022" path="/rpm" name="intel-vtune-amplifier-xe-2017-cli-17.3-510739.i486.rpm" cksum="3160439282"/>
    <file perm="0644" size="121944257" path="/rpm" name="intel-vtune-amplifier-xe-2017-cli-17.3-510739.x86_64.rpm" cksum="342159319"/>
    <file perm="0644" size="614748" path="/rpm" name="intel-vtune-amplifier-xe-2017-cli-common-17.3-510739.noarch.rpm" cksum="822745639"/>
    <file perm="0644" size="20406288" path="/rpm" name="intel-vtune-amplifier-xe-2017-collector-32linux-17.3-510739.i486.rpm" cksum="2834455036"/>
    <file perm="0644" size="36819481" path="/rpm" name="intel-vtune-amplifier-xe-2017-collector-64linux-17.3-510739.x86_64.rpm" cksum="3953942609"/>
    <file perm="0644" size="141310127" path="/rpm" name="intel-vtune-amplifier-xe-2017-common-17.3-510739.noarch.rpm" cksum="3583342227"/>
    <file perm="0644" size="19908491" path="/rpm" name="intel-vtune-amplifier-xe-2017-common-pset-17.3-510739.noarch.rpm" cksum="827402017"/>
    <file perm="0644" size="10952782" path="/rpm" name="intel-vtune-amplifier-xe-2017-doc-17.3-510739.noarch.rpm" cksum="757842848"/>
    <file perm="0644" size="63212112" path="/rpm" name="intel-vtune-amplifier-xe-2017-gui-17.3-510739.x86_64.rpm" cksum="3958541627"/>
    <file perm="0644" size="3671682" path="/rpm" name="intel-vtune-amplifier-xe-2017-gui-common-17.3-510739.noarch.rpm" cksum="876681611"/>
    <file perm="0644" size="489824" path="/rpm" name="intel-vtune-amplifier-xe-2017-sep-17.3-510739.noarch.rpm" cksum="583191555"/>
    <file perm="0644" size="8241885" path="/rpm" name="intel_clck_analyzer-2017.2-20170117.x86_64.rpm" cksum="169760155"/>
    <file perm="0644" size="25039812" path="/rpm" name="intel_clck_collector-2017.2-20170117.x86_64.rpm" cksum="2627599032"/>
    <file perm="0644" size="12354915" path="/rpm" name="intel_clck_common-2017.2-20170117.x86_64.rpm" cksum="275419086"/>
    <file perm="0644" size="19155784" path="/rpm" name="intel_clck_common-pset-2017.2-20170117.noarch.rpm" cksum="4154472157"/>
    <file perm="0644" size="12557" path="/rpm" name="intel_clck_support-2017.2-20170117.noarch.rpm" cksum="826070687"/>
</root>
